django_currency_converter/__init__.py
django_currency_converter/forms.py
django_currency_converter/urls.py
django_currency_converter/utils.py
django_currency_converter/views.py
django_currency_converter-0.1.0.dist-info/METADATA
django_currency_converter-0.1.0.dist-info/WHEEL
django_currency_converter-0.1.0.dist-info/top_level.txt
django_currency_converter-0.1.0.dist-info/RECORD
